nuztf/TNS_submit.py
nuztf/__init__.py
nuztf/ampel/__init__.py
nuztf/ampel/ampel_catalog.py
nuztf/ampel/ampel_cone.py
nuztf/ampel/ampel_cutout.py
nuztf/ampel/ampel_healpix.py
nuztf/ampel/ampel_lightcurve.py
nuztf/ampel/ampel_timerange.py
nuztf/ampel/urls.py
nuztf/ampel/utils.py
nuztf/api.py
nuztf/base_scanner.py
nuztf/cat_match.py
nuztf/cli.py
nuztf/config/gw_run_config.yaml
nuztf/config/nu_run_config.yaml
nuztf/credentials.py
nuztf/flatpix.py
nuztf/fritz.py
nuztf/irsa.py
nuztf/kowalski/__init__.py
nuztf/kowalski/config.py
nuztf/kowalski/kowalski_api.py
nuztf/kowalski/kowalski_cutout.py
nuztf/kowalski/kowalski_skymap.py
nuztf/neutrino_scanner.py
nuztf/observations/__init__.py
nuztf/observations/core.py
nuztf/observations/depot.py
nuztf/observations/master_log.py
nuztf/observations/mns.py
nuztf/observations/shared.py
nuztf/observations/skyvision.py
nuztf/observations/tap.py
nuztf/parse_nu_gcn.py
nuztf/paths.py
nuztf/plot.py
nuztf/skymap.py
nuztf/skymap_scanner.py
nuztf/style.py
nuztf/utils.py
nuztf-3.0.0.dist-info/LICENSE.txt
nuztf-3.0.0.dist-info/METADATA
nuztf-3.0.0.dist-info/WHEEL
nuztf-3.0.0.dist-info/entry_points.txt
nuztf-3.0.0.dist-info/RECORD
